Metadata-Version: 2.1
Name: autora-experiment-runner-firebase-prolific
Version: 1.0.1
Summary: AutoRA Firebase Prolific Experiment Runner provides experiment runners to run experiments with prolific and firebase
Author-email: Younes Strittmatter <younes_strittmatter@brown.edu>
License: MIT License
Project-URL: homepage, http://www.empiricalresearch.ai
Project-URL: repository, https://github.com/AutoResearch/autora-experiment-runner-firebase-prolific
Project-URL: documentation, https://autoresearch.github.io/autora/
Requires-Python: <4,>=3.8
License-File: LICENSE
Requires-Dist: autora-core
Requires-Dist: autora-experiment-runner-recruitment-manager-prolific
Requires-Dist: autora-experiment-runner-experimentation-manager-firebase
Provides-Extra: dev
Requires-Dist: autora-core[dev]; extra == "dev"
